logging_ext/__init__.py
logging_ext/handlers.py
logging_ext/py.typed
logging_ext_ramwin-0.2.2.dist-info/METADATA
logging_ext_ramwin-0.2.2.dist-info/WHEEL
logging_ext_ramwin-0.2.2.dist-info/licenses/LICENCE
logging_ext_ramwin-0.2.2.dist-info/RECORD
