Metadata-Version: 2.4
Name: logging_ext_ramwin
Version: 0.2.2
Summary: Extended logging handlers with date-based filename formatting
Project-URL: Homepage, https://github.com/ramwin/logging-ext-ramwin
Project-URL: Repository, https://github.com/ramwin/logging-ext-ramwin
Project-URL: Issues, https://github.com/ramwin/logging-ext-ramwin/issues
Author-email: ramwin <ramwin@qq.com>
License-Expression: MIT
License-File: LICENCE
Keywords: concurrent,date,handler,logging,rotation
Classifier: Development Status :: 4 - Beta
Classifier: Intended Audience :: Developers
Classifier: License :: OSI Approved :: MIT License
Classifier: Programming Language :: Python :: 3
Classifier: Programming Language :: Python :: 3.7
Classifier: Programming Language :: Python :: 3.8
Classifier: Programming Language :: Python :: 3.9
Classifier: Programming Language :: Python :: 3.10
Classifier: Programming Language :: Python :: 3.11
Classifier: Programming Language :: Python :: 3.12
Classifier: Topic :: Software Development :: Libraries :: Python Modules
Classifier: Topic :: System :: Logging
Requires-Python: >=3.7
